macen/__init__.py
macen/__main__.py
macen/auth.py
macen/challenges.py
macen/config.py
macen/exceptions.py
macen/manager.py
macen/py.typed
macen/server.py
macen/storages.py
macen-0.5.0.dist-info/WHEEL
macen-0.5.0.dist-info/entry_points.txt
macen-0.5.0.dist-info/METADATA
macen-0.5.0.dist-info/RECORD
