Metadata-Version: 2.4
Name: macen
Version: 0.5.0
Summary: Basic Python Server to execute ACME on behalf of dumb clients
Keywords: acme,server,client,proxy,letsencrypt
Author: Malte Swart
Author-email: Malte Swart <mswart@devtation.de>
License-Expression: GPL-3.0-or-later
Classifier: Development Status :: 5 - Production/Stable
Classifier: Intended Audience :: System Administrators
Classifier: Topic :: Internet :: WWW/HTTP :: HTTP Servers
Classifier: Topic :: Security :: Cryptography
Classifier: Topic :: System :: Networking
Classifier: Topic :: System :: Systems Administration
Classifier: Topic :: Utilities
Classifier: License :: OSI Approved :: GNU General Public License v3 (GPLv3)
Classifier: Programming Language :: Python :: 3 :: Only
Classifier: Programming Language :: Python :: 3
Classifier: Programming Language :: Python :: 3.10
Classifier: Programming Language :: Python :: 3.11
Classifier: Programming Language :: Python :: 3.12
Classifier: Programming Language :: Python :: 3.13
Requires-Dist: acme>=0.21.0
Requires-Dist: josepy
Requires-Dist: ipy
Requires-Dist: pydantic>=2.11.7
Requires-Dist: dnslib ; extra == 'dns01'
Requires-Dist: py3dns ; extra == 'dns01'
Requires-Dist: systemd ; extra == 'systemd'
Requires-Python: >=3.10
Project-URL: Changelog, https://github.com/mswart/macen/blob/master/CHANGELOG.rst
Project-URL: Issues, https://github.com/mswart/macen/issues
Project-URL: Repository, https://github.com/mswart/macen
Provides-Extra: dns01
Provides-Extra: systemd
